{
  "achievement_mission": [
    {
      "group": 1,
      "group_name": "achievement_groupName_1",
      "achievement": 1,
      "list": [
        {
          "mission": 1,
          "icon": 2,
          "name": "rank_name_2",
          "objective": 20,
          "reward_type": 21,
          "reward": 102,
          "reward_amount": 1
        },
        {
          "mission": 2,
          "icon": 3,
          "name": "rank_name_3",
          "objective": 50,
          "reward_type": 21,
          "reward": 103,
          "reward_amount": 1
        },
        {
          "mission": 3,
          "icon": 4,
          "name": "rank_name_4",
          "objective": 80,
          "reward_type": 21,
          "reward": 104,
          "reward_amount": 1
        },
        {
          "mission": 4,
          "icon": 5,
          "name": "rank_name_5",
          "objective": 120,
          "reward_type": 21,
          "reward": 105,
          "reward_amount": 1
        }
      ]
    },
    {
      "group": 2,
      "group_name": "achievement_groupName_2",
      "achievement": 1,
      "list": [
        {
          "mission": 5,
          "icon": 6,
          "name": "rank_name_6",
          "objective": 200,
          "reward_type": 21,
          "reward": 106,
          "reward_amount": 1
        },
        {
          "mission": 6,
          "icon": 7,
          "name": "rank_name_7",
          "objective": 300,
          "reward_type": 21,
          "reward": 107,
          "reward_amount": 1
        },
        {
          "mission": 7,
          "icon": 8,
          "name": "rank_name_8",
          "objective": 400,
          "reward_type": 21,
          "reward": 108,
          "reward_amount": 1
        },
        {
          "mission": 8,
          "icon": 9,
          "name": "rank_name_9",
          "objective": 500,
          "reward_type": 21,
          "reward": 109,
          "reward_amount": 1
        },
        {
          "mission": 9,
          "icon": 10,
          "name": "rank_name_10",
          "objective": 600,
          "reward_type": 21,
          "reward": 110,
          "reward_amount": 1
        },
        {
          "mission": 10,
          "icon": 11,
          "name": "rank_name_11",
          "objective": 700,
          "reward_type": 21,
          "reward": 111,
          "reward_amount": 1
        },
        {
          "mission": 11,
          "icon": 12,
          "name": "rank_name_12",
          "objective": 800,
          "reward_type": 21,
          "reward": 112,
          "reward_amount": 1
        },
        {
          "mission": 12,
          "icon": 13,
          "name": "rank_name_13",
          "objective": 900,
          "reward_type": 21,
          "reward": 113,
          "reward_amount": 1
        },
        {
          "mission": 13,
          "icon": 14,
          "name": "rank_name_14",
          "objective": 1100,
          "reward_type": 21,
          "reward": 114,
          "reward_amount": 1
        },
        {
          "mission": 14,
          "icon": 15,
          "name": "rank_name_15",
          "objective": 1300,
          "reward_type": 21,
          "reward": 115,
          "reward_amount": 1
        }
      ]
    },
    {
      "group": 3,
      "group_name": "achievement_groupName_3",
      "achievement": 1,
      "list": [
        {
          "mission": 15,
          "icon": 16,
          "name": "rank_name_16",
          "objective": 1500,
          "reward_type": 21,
          "reward": 116,
          "reward_amount": 1
        },
        {
          "mission": 16,
          "icon": 17,
          "name": "rank_name_17",
          "objective": 1700,
          "reward_type": 21,
          "reward": 117,
          "reward_amount": 1
        },
        {
          "mission": 17,
          "icon": 18,
          "name": "rank_name_18",
          "objective": 1900,
          "reward_type": 21,
          "reward": 118,
          "reward_amount": 1
        },
        {
          "mission": 18,
          "icon": 19,
          "name": "rank_name_19",
          "objective": 2100,
          "reward_type": 21,
          "reward": 119,
          "reward_amount": 1
        },
        {
          "mission": 19,
          "icon": 20,
          "name": "rank_name_20",
          "objective": 2300,
          "reward_type": 21,
          "reward": 120,
          "reward_amount": 1
        },
        {
          "mission": 20,
          "icon": 21,
          "name": "rank_name_21",
          "objective": 2500,
          "reward_type": 21,
          "reward": 121,
          "reward_amount": 1
        },
        {
          "mission": 21,
          "icon": 22,
          "name": "rank_name_22",
          "objective": 2750,
          "reward_type": 21,
          "reward": 122,
          "reward_amount": 1
        },
        {
          "mission": 22,
          "icon": 23,
          "name": "rank_name_23",
          "objective": 3000,
          "reward_type": 21,
          "reward": 123,
          "reward_amount": 1
        },
        {
          "mission": 23,
          "icon": 24,
          "name": "rank_name_24",
          "objective": 3250,
          "reward_type": 21,
          "reward": 124,
          "reward_amount": 1
        },
        {
          "mission": 24,
          "icon": 25,
          "name": "rank_name_25",
          "objective": 3500,
          "reward_type": 21,
          "reward": 125,
          "reward_amount": 1
        }
      ]
    },
    {
      "group": 4,
      "group_name": "achievement_groupName_4",
      "achievement": 1,
      "list": [
        {
          "mission": 25,
          "icon": 26,
          "name": "rank_name_26",
          "objective": 3750,
          "reward_type": 21,
          "reward": 126,
          "reward_amount": 1
        },
        {
          "mission": 26,
          "icon": 27,
          "name": "rank_name_27",
          "objective": 4000,
          "reward_type": 21,
          "reward": 127,
          "reward_amount": 1
        },
        {
          "mission": 27,
          "icon": 28,
          "name": "rank_name_28",
          "objective": 4250,
          "reward_type": 21,
          "reward": 128,
          "reward_amount": 1
        },
        {
          "mission": 28,
          "icon": 29,
          "name": "rank_name_29",
          "objective": 4500,
          "reward_type": 21,
          "reward": 129,
          "reward_amount": 1
        },
        {
          "mission": 29,
          "icon": 30,
          "name": "rank_name_30",
          "objective": 4750,
          "reward_type": 21,
          "reward": 130,
          "reward_amount": 1
        },
        {
          "mission": 30,
          "icon": 31,
          "name": "rank_name_31",
          "objective": 5000,
          "reward_type": 21,
          "reward": 131,
          "reward_amount": 1
        },
        {
          "mission": 31,
          "icon": 32,
          "name": "rank_name_32",
          "objective": 5250,
          "reward_type": 21,
          "reward": 132,
          "reward_amount": 1
        },
        {
          "mission": 32,
          "icon": 33,
          "name": "rank_name_33",
          "objective": 5500,
          "reward_type": 21,
          "reward": 133,
          "reward_amount": 1
        },
        {
          "mission": 33,
          "icon": 34,
          "name": "rank_name_34",
          "objective": 5750,
          "reward_type": 21,
          "reward": 134,
          "reward_amount": 1
        },
        {
          "mission": 34,
          "icon": 35,
          "name": "rank_name_35",
          "objective": 6000,
          "reward_type": 21,
          "reward": 135,
          "reward_amount": 1
        }
      ]
    },
    {
      "group": 5,
      "group_name": "achievement_groupName_5",
      "achievement": 1,
      "list": [
        {
          "mission": 35,
          "icon": 36,
          "name": "rank_name_36",
          "objective": 6250,
          "reward_type": 21,
          "reward": 136,
          "reward_amount": 1
        },
        {
          "mission": 36,
          "icon": 37,
          "name": "rank_name_37",
          "objective": 6500,
          "reward_type": 21,
          "reward": 137,
          "reward_amount": 1
        },
        {
          "mission": 37,
          "icon": 38,
          "name": "rank_name_38",
          "objective": 7000,
          "reward_type": 21,
          "reward": 138,
          "reward_amount": 1
        },
        {
          "mission": 38,
          "icon": 39,
          "name": "rank_name_39",
          "objective": 7500,
          "reward_type": 21,
          "reward": 139,
          "reward_amount": 1
        },
        {
          "mission": 39,
          "icon": 40,
          "name": "rank_name_40",
          "objective": 8000,
          "reward_type": 21,
          "reward": 140,
          "reward_amount": 1
        }
      ]
    }
  ]
}